{
  "name": "Andrew S. Miner",
  "homepage": "http://www.cs.iastate.edu/~asminer",
  "status": "success",
  "content": "Andrew S Miner Skip to main content Andrew S Miner Position Associate Professor, Department of Computer Science Contact Email asminer@iastate.edu Phone 515-294-2392 233 Atanasoff 2434 Osborn Dr. Ames, IA 50011-1090 Download CV Social Media and Websites LinkedIn ORCID Education PhD., Computer Science, College of William and Mary, 2000",
  "content_length": 335,
  "method": "requests",
  "crawl_time": "2025-12-01 12:57:49"
}