{
  "name": "Chen Yu 0001",
  "homepage": "https://psych.indiana.edu/directory/faculty/yu-chen.html",
  "status": "success",
  "content": "Chen Yu: Faculty: Directory: Psychological and Brain Sciences: Indiana University Bloomington Skip to Content Skip to Main Navigation Skip to Search ContactStudent Portal HomeDirectoryFacultyChen Yu Chen YuAdjunct Professor, Psychological and Brain SciencesCharles and Sarah Seay Regents Professor of Developmental Psychology, University of Texas at Austinchenyu@iu.eduOffice Hours M-FBy Appointment Only Faculty + Staff IntranetPsychological and Brain Sciences social media channelsTwitterFacebookInstagramYouTube College of Arts & SciencesDepartment of Psychological and Brain SciencesThe College of Arts & Sciences The College of Arts & Sciences Contact Student Portal Undergraduate Clinical Psychological Science B.S. Neuroscience B.S. Organizational + Business Psychology B.S. Psychology B.A. Psychology B.S. Minor + Certificates Psychology Minor Neuroscience Certificate Areas of Interest AdvisingAdvisors Academic Support Research Opportunities Career Preparation + Advising Service-Learning + Practica Volunteer Opportunities Tutoring + Teaching Internships Internships Graduate & Professional Program Preparation Applying to Graduate School Financing Graduate School Honors Program Graduate Ph.D. Degree Qualifying Exams Candidacy Dissertation Research Project Double Major Ph.D. Minor Funding Opportunities Advising Courses Support Services Meeting Room Reservations Physical Plant Service Requests Poster Printing Undergraduate Teaching Assistant Assignments Participate in Experiments",
  "content_length": 1496,
  "method": "requests",
  "crawl_time": "2025-12-01 12:50:51"
}