{
  "name": "David Hästbacka",
  "homepage": "https://www.tuni.fi/en/david-hastbacka",
  "status": "success",
  "content": "David Hästbacka | Tampere universitiesDavid HästbackaAssociate Professor (tenure track), OhjelmistotekniikkaFaculty of Information Technology and Communication Sciences | Computing SciencesTampere Universitydavid.hastbacka [at] tuni.fi (david[dot]hastbacka[at]tuni[dot]fi)phone number+358405191506Hervanta CampusAbout meLeading a research group in the field of software engineering and informatics applied to industrial automation, production and energy systems. Research focus on system architecture, information system composition and integration platforms, and semantics for networked systems and services. Teaching and supervision related to Web and Cloud architectures and dependable IoT systems. Ongoing projects:Hedge-IoT (Horizon Europe, 2024-2027)TwinfFlow (Business Finland, 2024-2027)Arrowhead fPVN (EU Chips JU/Business Finland, 2023-2026)DAZE (Business Finland, 2023-2026)Metawave (Horizon Europe, 2024-2028)GenerIoT (ITEA4/Business Finland, 2023-2025)Industry X (Business Finland, 2022-2025)TRINEFLEX (Horizon Europe, 2022-2026)INGA (Integrated automation for distribution grid and DERs, Business Finland, 2022-2024)AeroPolis (Academy of Finland, 2022-2024)Past projects:FEMMa (Future Electrified Mobile Machines, Business Finland, 2021-2024)DisMa (Distributed Management of Electricity System, Academy of Finland, 2019-2023)NIC (Nordic Interoperability Collaboration, Business Finland, 2021)Productive4.0 (EC ECSEL/Business Finland, 2017-2020)AIDOMUS (Research to business, Business Finland, 2019-2020)SEMIS (Semantic Interoperability of Industrial Systems, Academy of Finland Postdoctoral Researcher, 2017-2020)COCOP (Coordinating Optimisation of Complex Industrial Processes, EU H2020, 2016-2020)USE (Urban Smart Energy, Business Finland, 2017-2019)S-Step (Business Finland, 2016-2017)Arrowhead (EC ECSEL, 2013-2017)",
  "content_length": 1833,
  "method": "requests",
  "crawl_time": "2025-12-01 12:59:13"
}