{
  "name": "J. M. Akkermans",
  "homepage": "http://www.cs.vu.nl/~hansa",
  "status": "success",
  "content": "Welcome by Hans Akkermans Prof.Dr. Hans Akkermans Faculty of Sciences Section Business Informatics FEW/BI Free University Amsterdam Research: Business Informatics (BI) URL: http://www.cs.vu.nl/~hansa Teaching: Information Science / IS (Informatiekunde) Phone: +31 20 44 47718 Fax: +31 20 444 7728 Address:Free University Amsterdam VUA Faculty of Sciences (FEW) Section Business Informatics (BI) De Boelelaan 1081a, NL-1081 HV Amsterdam, The NetherlandsRoom U3.31",
  "content_length": 462,
  "method": "requests",
  "crawl_time": "2025-12-01 13:24:41"
}