{
  "name": "Robert Sámal",
  "homepage": "https://iuuk.mff.cuni.cz/~samal",
  "status": "success",
  "content": "Robert Šámal | Charles University Robert Šámal Home Research Mathematics++ book Výuka/Teaching Current position Associate professor at Computer Science Institute at the Faculty of Mathematics and Physics of the Charles University. Short bio. I studied at Charles University with Jarik Nešetřil as advisor, obtaining PhD in 2006. I spent two years as a PIMS postdoc at Simon Fraser University, working with Bojan Mohar, Pavol Hell and Matt DeVos. Since 2008 I'm working at Charles University. My research interests cover many areas in discrete mathematics and theoretical computer science. Longer cv in English and in Czech. I've been co-organizing the 52nd Czech-Slovak Conference on Combinatorics and Graph Theory. Open problem garden Wikipedia-style collection of open problems, mainly in discrete math, that I started with Matt DeVos and Bojan Mohar. Contact email: address: Computer Science Institute, Charles University, Malostranske nam. 25, 118 00 Praha 1, Czech Republic in person: the address above, 3rd floor, room 323",
  "content_length": 1028,
  "method": "requests",
  "crawl_time": "2025-12-01 14:19:10"
}