{
  "name": "Sandra Siby",
  "homepage": "https://nyuad.nyu.edu/en/academics/divisions/engineering/faculty/sandra-siby.html",
  "status": "success",
  "content": "Sandra Siby - NYU Abu Dhabi Skip To All NYU Navigation Skip To Main Content To open and close this bar, use optionalt+/ Sandra Siby Assistant Professor of Computer Engineering, NYU Abu Dhabi; Associated Faculty with the Computer Science and Engineering Department, NYU Tandon Affiliation: NYU Abu Dhabi Education: PhD, Ecole Polytechnique Fédérale de Lausanne (EPFL) sandra.siby@nyu.edu Research Websites: Haven Lab Research Areas: Cybersecurity; privacy Visit Sandra Siby's Personal Website Sandra Siby is an Assistant Professor of Computer Engineering at NYUAD. She obtained her PhD (Computer Science) from EPFL, her MS (Electrical Engineering) from ETH Zurich, and her BEng (Electrical Engineering) from the National University of Singapore. Sandra's research interests lie in the fields of security and privacy. Her research goal is to provide individuals with better control over their privacy and protection from digital threats. She wants to work towards a future where digital services are inherently designed with user privacy and security at the forefront. Her current areas of focus are security and privacy mechanisms for the web/IoT/other emerging technologies, and deployment of trusted and private machine learning on edge devices. Prior to NYUAD, Sandra was a postdoctoral research associate at Imperial College London. Sandra also spent a few years as a research engineer at the Singapore University of Technology and Design, and as a technology analyst at J.P. Morgan. Courses Taught Expand/Collapse all",
  "content_length": 1521,
  "method": "requests",
  "crawl_time": "2025-12-01 14:23:40"
}