{
  "name": "Shadan Sadeghian Borojeni",
  "homepage": "https://www.mediacoop.uni-siegen.de/de/personen/sadedhian-shadan",
  "status": "success",
  "content": "Sadeghian, Shadan, Jun.-Prof. Dr.-Ing. » SFB 1187 – Medien der Kooperation Sadeghian, Shadan, Jun.-Prof. Dr.-Ing. – SFB 1187 – Medien der Kooperation Sadeghian, Shadan, Jun.-Prof. Dr.-Ing. P05 und MGK Teilprojektleiterin E-Mail Webseite Zum Teilprojekt P05 Zum Teilprojekt MGK Vita Shadan Sadeghian ist Juniorprofessorin für Interaktive Autonome Systeme an der Universität Siegen. Sie studierte Informatik an der Universität Bonn und der RWTH Aachen und promovierte im Bereich Human-Computer Interaction am OFFIS Institut für Informationstechnik und der Universität Oldenburg. Darüber hinaus arbeitete sie als Doktorandin am Max-Planck-Institut in Tübingen und als Post-Doc am Fraunhofer-Institut FKIE sowie in der Arbeitsgruppe Experience and Interaction an der Universität Siegen. Ihre Forschung konzentriert sich auf die Gestaltung von Nutzererfahrungen und Interaktion mit automatisierten Systemen wie Robotern, KI-basierten Systemen und automatisierten Fahrzeugen. Sie untersucht Ansätze, die pragmatische (leistungsorientierte) und hedonische (erlebnisorientierte) Qualitäten der Interaktion mit Automatisierung ausbalancieren. Publikationen Publikationen auf Google Scholar",
  "content_length": 1180,
  "method": "requests",
  "crawl_time": "2025-12-01 14:26:09"
}