{
  "name": "Simone L. Martins",
  "homepage": "http://www2.ic.uff.br/~simone",
  "status": "success",
  "content": "Simone de Lima Martins Simone de Lima Martins Professora Associada, Departamento de Ciência da Computação, Instituto de Computação email: simone@ic.uff.br CV (Lattes) Cursos 2019.2 Arquiteturas de Computadores Sistemas Distribuídos Cursos 2019.1 Sistemas de Computação Sistemas Distribuídos Cursos 2018.2 Fundamentos de Arquiteturas de Computadores Laboratório de Programação Paralela Cursos 2018.1 Programação de Computadores II para SI Cursos 2017.2 Arquiteturas de Computadores Programação de Computadores IV Laboratório de Programação Paralela Cursos 2017.1 Programação de Computadores I Cursos 2016.2 Sistemas de Computação (Cuiabá)",
  "content_length": 637,
  "method": "requests",
  "crawl_time": "2025-12-01 14:28:57"
}