{
  "name": "Wesley K. G. Assunção",
  "homepage": "https://wesleyklewerton.github.io",
  "status": "success",
  "content": "Wesley K. G. Assuncao Wesley K. G. Assunção Home CV Publications Visitors\\Supervisions\\Teaching Wesley Klewerton Guez Assunção Associate Professor with the Department of Computer Science at North Carolina State University. Co-editor of the In Practice track at the Journal of Systems and Software Chess Player (FIDE profile - lichess.org) Research Interests Software Modernization: reverse engineering, re-engineering, and migration Variability Management: variability mechanisms, software customization, and software reuse (SPLs/HCSs) Software Quality: technical debt, code smells, and software refactoring Model-Driven Engineering: model inconsistency detection, repair generation, and change propagation Collaboration in Systems Engineering: change synchronization, tool flexibility, and conflict awareness Software Testing: regression testing, integration testing, and test case selection/prioritization AI4SE: Generative AI, Machine Learning, and Evolutionary Algorithms for Software Engineering Contact Department of Computer Science, North Carolina State University 890 Oval Drive - Engineering Building II. Raleigh, NC 27695, USA Office 3228: Wolfpack Innovations in Software Engineering Research (WISER) Lab Email: wguezas (at) ncsu.edu | Phone: +1 (919) 513-3666 LinkedIn: https://www.linkedin.com/in/wesley-kg-assuncao/ X (Twitter): @wesleyklewerton",
  "content_length": 1360,
  "method": "requests",
  "crawl_time": "2025-12-01 14:46:32"
}